{
  "_readme": [
    "記事に埋める図版のデータ。描画は site/figures.mjs が行います。",
    "",
    "【使い方】",
    "  記事の Markdown に次の1行を書くと、その位置に図版が入ります:",
    "      ::figure:retinol-dropout::",
    "",
    "【★ 絶対のルール】",
    "  ここに書いてよい数値は、articles/*.md に実際に書かれている数値だけです。",
    "  図版のために新しい数字を計算したり、記憶で補ったりしないこと。",
    "  source（出典）は必ず添えること。",
    "",
    "【type】",
    "  bar     … 横棒（1系列）。rows に label と value。max で軸の上限。refLine で基準線",
    "  grouped … 横棒（2系列）。series に系列名2つ、rows に values を2つ",
    "  matrix  … 2列の対比表。cols（2列）と rows（label + cells）",
    "  ladder  … 順位はあるが数量ではないもの。rows に strength(1-4) と name と note",
    "",
    "【pending】",
    "  値が確定していないもの（「観察期間内に戻らなかった」など）は pending: true。",
    "  実測値と同じ塗りにしないため。"
  ],

  "figures": {
    "pdrn-coi": {
      "type": "matrix",
      "title": "「利益相反なし」と書いた論文の、著者の所属を見る",
      "cols": ["論文に書かれた申告", "同じ論文に印刷された所属・資金"],
      "rows": [
        { "label": "リジュランの第III相試験（2014・撤回済み）", "cells": [{ "on": false, "text": "全著者に金銭的関与なし" }, { "on": true, "text": "著者1名がメーカーのR&Dセンター所属。2016年に撤回" }] },
        { "label": "PDRN外用＋VC＋ナイアシンアミド（2022・動物実験）", "cells": [{ "on": false, "text": "利益相反なし" }, { "on": true, "text": "資金提供は I'll Global 社。著者1名が同社所属" }] },
        { "label": "PCL vs リジュラン（2025・撤回済み）", "cells": [{ "on": false, "text": "利益相反なし" }, { "on": true, "text": "資金提供は DexLevo 社。2026年に撤回" }] },
        { "label": "塗るPDRNの唯一のヒト試験（2026）", "cells": [{ "on": false, "text": "利益相反なし・資金提供なし" }, { "on": true, "text": "著者5名中3名が化粧品・バイオ企業2社の所属" }] },
        { "label": "PNフィラー vs ヒアルロン酸（2022）", "cells": [{ "on": false, "text": "記載なし" }, { "on": false, "text": "著者11名全員が大学病院。企業所属者なし" }] }
      ],
      "source": "出典: 各論文のPubMed公式API（E-utilities）の記録。著者所属・利益相反・資金提供の記載を1本ずつ確認（2026-07-13）。企業の資金が入ること自体は普通のことです。問題は、それを「なし」と書くことのほうです"
    },

    "sunscreen-amount": {
      "type": "bar",
      "title": "日焼け止めは、基準の何割しか塗られていないのか",
      "unit": "単位: mg/cm²",
      "max": 2.2,
      "refLine": { "value": 2.0, "label": "SPFを測るときの基準量 2.0 mg/cm²。ここに届いて、はじめて表示どおりのSPFが出る" },
      "rows": [
        { "label": "乳液タイプ", "value": 0.3 },
        { "label": "下地クリーム", "value": 0.5 },
        { "label": "スプレー", "value": 0.5 },
        { "label": "ジェル", "value": 1.2 }
      ],
      "source": "出典: Marume 2020（日本化粧品技術者会誌、日本人女性131人の実測）"
    },

    "collagen-funding": {
      "type": "matrix",
      "title": "同じ23件の試験。資金提供元で分けると、結果が入れ替わる",
      "cols": ["企業の資金あり", "企業の資金なし"],
      "rows": [
        { "label": "皮膚の水分量", "cells": [{ "on": true, "text": "有意な改善" }, { "on": false, "text": "差なし" }] },
        { "label": "弾力", "cells": [{ "on": true, "text": "有意な改善" }, { "on": false, "text": "差なし" }] },
        { "label": "シワ", "cells": [{ "on": true, "text": "有意な改善" }, { "on": false, "text": "差なし" }] }
      ],
      "source": "出典: Myung & Park 2025（Am J Med、23件のRCT・のべ1,474人）"
    },

    "bathing-nolotion": {
      "type": "grouped",
      "title": "「速さ」ではなく「塗るか塗らないか」だった",
      "series": ["アトピー群", "健常群"],
      "unit": "入浴前を100としたときの、90分間の平均角層水分量",
      "max": 220,
      "refLine": { "value": 100, "label": "入浴前 = 100。この線を下回ったのは、無塗布の条件だけ。直後と30分後は、ほとんど変わらない" },
      "rows": [
        { "label": "入浴のみ・無塗布", "values": [91.4, 94.6] },
        { "label": "入浴＋直後に塗る", "values": [141.6, 168.8] },
        { "label": "入浴＋30分後に塗る", "values": [141.0, 178.6] },
        { "label": "入浴なし・塗るだけ", "values": [206.2, 215.0] }
      ],
      "source": "出典: 記事末尾の参考文献を参照"
    },

    "retinol-dropout": {
      "type": "bar",
      "title": "肌に合わずに、使用をやめた人の数",
      "unit": "218人が6週間、自宅でレチノールを使った試験",
      "max": 26,
      "rows": [
        { "label": "0.3% を使った群", "value": 4, "display": "4人" },
        { "label": "1% を使った群", "value": 23, "display": "23人" }
      ],
      "source": "肌の反応が「なし、または軽度」で済んだ人は、0.3%群 88.7% に対して 1%群 62.1%（p<0.0001）"
    },

    "vitc-evidence": {
      "type": "ladder",
      "title": "ヒトでの根拠の強さで、並べ替える",
      "rows": [
        { "strength": 4, "name": "ピュアなL-アスコルビン酸", "note": "複数の二重盲検RCTと、システマティックレビューがある" },
        { "strength": 3, "name": "リン酸アスコルビルNa（SAP）", "note": "ヒトRCTあり。ただし測ったのはニキビで、シワでも色素沈着でもない" },
        { "strength": 2, "name": "リン酸アスコルビルMg（MAP）", "note": "1996年の、対照群のない試験が1本（34人中19人）" },
        { "strength": 1, "name": "VC-IP / アスコルビルグルコシド / 3-O-エチルアスコルビン酸", "note": "単独のヒトRCTを、今回の調査では確認できず" }
      ],
      "source": "「最新」「高浸透」と書かれた成分ほど、下に来る。広告が強い成分と、根拠が強い成分は別物です"
    },

    "ha-fate": {
      "type": "bar",
      "title": "飲んだヒアルロン酸の炭素は、どこへ行ったのか",
      "unit": "168時間までの排泄の内訳",
      "max": 80,
      "rows": [
        { "label": "呼気（吐く息）", "value": 76.5, "display": "76.5%" },
        { "label": "糞", "value": 11.9, "display": "11.9%" },
        { "label": "尿", "value": 3.0, "display": "3.0%" }
      ],
      "source": "ラットに標識したヒアルロン酸を飲ませた実験です。ヒトの皮膚で確かめたデータではありません"
    },

    "fasting-recovery": {
      "type": "bar",
      "title": "保湿をやめた肌が、もとに戻るまでの日数",
      "unit": "日",
      "max": 23,
      "rows": [
        { "label": "17〜25歳（客観評価）", "value": 6, "display": "6日" },
        { "label": "17〜25歳（自己評価）", "value": 10, "display": "10日" },
        { "label": "15〜20歳（夏）", "value": 11, "display": "11日" },
        { "label": "40〜55歳", "value": 21, "display": "戻らず", "pending": true }
      ],
      "source": "出典: Maul 2020（分割顔パイロット試験）。40〜55歳群は21日間の観察期間内に有意な回復が見られなかった。ただし13人と小さな群です"
    },

    "turnover-days": {
      "type": "bar",
      "title": "ターンオーバーを実際に測った研究が出した日数",
      "unit": "日（「28日」を実測した論文は、PubMed で見つかりませんでした）",
      "max": 55,
      "rows": [
        { "label": "よく言われる「28日」", "value": 28, "display": "0件", "pending": true },
        { "label": "Weinstein 1984（表皮全体）", "value": 39, "display": "39日" },
        { "label": "Bergstresser & Taylor 1977", "value": 45, "display": "45日" },
        { "label": "Iizuka 1994（同じデータの再計算）", "value": 48, "display": "47〜48日" }
      ],
      "source": "「28日」の棒は、実測値ではなく「その数字を報告した論文が0件だった」ことを示しています（斜線）"
    }
  }
}
